flux_restful_client/__init__.py
flux_restful_client/defaults.py
flux_restful_client/logger.py
flux_restful_client/settings.yml
flux_restful_client/version.py
flux_restful_client/client/__init__.py
flux_restful_client/client/cancel.py
flux_restful_client/client/config.py
flux_restful_client/client/info.py
flux_restful_client/client/listing.py
flux_restful_client/client/logs.py
flux_restful_client/client/shell.py
flux_restful_client/client/stop.py
flux_restful_client/client/submit.py
flux_restful_client/main/__init__.py
flux_restful_client/main/client.py
flux_restful_client/main/schemas.py
flux_restful_client/main/settings.py
flux_restful_client/tests/test_api.py
flux_restful_client/utils/__init__.py
flux_restful_client/utils/auth.py
flux_restful_client/utils/fileio.py
flux_restful_client/utils/misc.py
flux_restful_client/utils/terminal.py
flux_restful_client-0.2.1.dist-info/LICENSE
flux_restful_client-0.2.1.dist-info/METADATA
flux_restful_client-0.2.1.dist-info/WHEEL
flux_restful_client-0.2.1.dist-info/entry_points.txt
flux_restful_client-0.2.1.dist-info/top_level.txt
flux_restful_client-0.2.1.dist-info/RECORD
