Metadata-Version: 2.1
Name: flux-restful-client
Version: 0.2.1
Summary: Python functions and command line equivalent for interacting with Flux RESTful API.
Home-page: https://github.com/flux-framework/flux-restful-api/tree/main/clients/python
Author: Vanessa Sochat
Author-email: vsoch@users.noreply.github.com
Maintainer: Vanessa Sochat
License: LICENSE
Keywords: flux,flux framework,client,RESTFul API
Classifier: Intended Audience :: Science/Research
Classifier: Intended Audience :: Developers
Classifier: License :: OSI Approved :: GNU Lesser General Public License v3 (LGPLv3)
Classifier: Programming Language :: Python
Classifier: Topic :: Software Development
Classifier: Topic :: Scientific/Engineering
Classifier: Operating System :: Unix
Classifier: Programming Language :: Python :: 3.8
License-File: LICENSE
Requires-Dist: ruamel.yaml
Requires-Dist: httpx
Requires-Dist: jsonschema
Requires-Dist: python-jose[cryptography]
Provides-Extra: all
Requires-Dist: ruamel.yaml ; extra == 'all'
Requires-Dist: httpx ; extra == 'all'
Requires-Dist: jsonschema ; extra == 'all'
Requires-Dist: python-jose[cryptography] ; extra == 'all'
Requires-Dist: pytest (>=4.6.2) ; extra == 'all'
